jp2curvtest/__init__.py
jp2curvtest/main.py
jp2curvtest-0.0.2.dist-info/LICENSE
jp2curvtest-0.0.2.dist-info/METADATA
jp2curvtest-0.0.2.dist-info/WHEEL
jp2curvtest-0.0.2.dist-info/top_level.txt
jp2curvtest-0.0.2.dist-info/RECORD
