Metadata-Version: 2.1
Name: jp2curvtest
Version: 0.0.2
Summary: A module to validate jp2images
Author-email: Kim Pham <kimpham54@gmail.com>
Project-URL: Homepage, https://pypi.org/project/jp2curvtest/
Project-URL: Issues, https://github.com/pypa/sampleproject/issues
Classifier: Programming Language :: Python :: 3
Classifier: License :: OSI Approved :: Apache Software License
Classifier: Operating System :: OS Independent
Requires-Python: >=3.10
License-File: LICENSE
